cubicweb_eac/__init__.py
cubicweb_eac/__pkginfo__.py
cubicweb_eac/ccplugin.py
cubicweb_eac/dataimport.py
cubicweb_eac/hooks.py
cubicweb_eac/schema.py
cubicweb_eac/sobjects.py
cubicweb_eac/testutils.py
cubicweb_eac/views.py
cubicweb_eac/entities/__init__.py
cubicweb_eac/entities/rdf.py
cubicweb_eac/i18n/en.po
cubicweb_eac/i18n/fr.po
cubicweb_eac/migration/0.2.0_Any.py
cubicweb_eac/migration/0.3.0_Any.py
cubicweb_eac/migration/0.3.1_Any.py
cubicweb_eac/migration/0.5.0_Any.py
cubicweb_eac/migration/0.5.1_Any.py
cubicweb_eac/migration/0.6.0_Any.py
cubicweb_eac/migration/0.8.0_Any.py
cubicweb_eac/migration/0.8.1_Any.py
cubicweb_eac/migration/0.9.0_Any.py
cubicweb_eac/migration/postcreate.py
cubicweb_eac-3.0.0.dist-info/METADATA
cubicweb_eac-3.0.0.dist-info/WHEEL
cubicweb_eac-3.0.0.dist-info/entry_points.txt
cubicweb_eac-3.0.0.dist-info/top_level.txt
cubicweb_eac-3.0.0.dist-info/RECORD
