Metadata-Version: 2.1
Name: cubicweb-eac
Version: 3.0.0
Summary: Implementation of Encoded Archival Context for CubicWeb
Home-page: https://forge.extranet.logilab.fr/cubicweb/cubes/eac
Author: LOGILAB S.A. (Paris, FRANCE)
Author-email: contact@logilab.fr
License: LGPL
Classifier: Environment :: Web Environment
Classifier: Framework :: CubicWeb
Classifier: Programming Language :: Python :: 3
Classifier: Programming Language :: Python :: 3 :: Only
Classifier: Programming Language :: JavaScript
Requires-Dist: cubicweb <5.0.0,>=4.0.0
Requires-Dist: cubicweb-web <2.0.0,>=1.0.0
Requires-Dist: cubicweb-prov <2.0.0,>=1.0.0
Requires-Dist: cubicweb-skos <4.0.0,>=3.0.0
Requires-Dist: cubicweb-addressbook <3.0.0,>=2.0.0
Requires-Dist: cubicweb-compound <2.0.0,>=1.0.0
Requires-Dist: python-dateutil
